kingsquit/__init__.py
kingsquit/__main__.py
kingsquit/downloader.py
kingsquit-0.1.3.dist-info/LICENSE
kingsquit-0.1.3.dist-info/METADATA
kingsquit-0.1.3.dist-info/WHEEL
kingsquit-0.1.3.dist-info/entry_points.txt
kingsquit-0.1.3.dist-info/top_level.txt
kingsquit-0.1.3.dist-info/RECORD
