Metadata-Version: 2.1
Name: kingsquit
Version: 0.1.3
Summary: A dialogue randomiser for videos.
Home-page: https://github.com/JMcB17/kingsquit
Author: JMcB
Author-email: joel.mcbride1@live.com
License: GPLv3
Platform: UNKNOWN
Classifier: Programming Language :: Python :: 3
Classifier: License :: OSI Approved :: GNU General Public License v3 (GPLv3)
Classifier: Development Status :: 3 - Alpha
Classifier: Environment :: Console
Requires-Python: >=3
Requires-Dist: ffmpeg-python
Requires-Dist: youtube-dl
Requires-Dist: pysrt
Requires-Dist: pycaption
Requires-Dist: cchardet
